dt_structures3x/__init__.py
dt_structures3x/binarytree.py
dt_structures3x/hashtable.py
dt_structures3x/linkedlist.py
data_structures3x-1.4.6.dist-info/LICENSE
data_structures3x-1.4.6.dist-info/METADATA
data_structures3x-1.4.6.dist-info/WHEEL
data_structures3x-1.4.6.dist-info/top_level.txt
data_structures3x-1.4.6.dist-info/RECORD
