Metadata-Version: 2.1
Name: data-structures3x
Version: 1.4.6
Summary: Python 3+ version data structures
Home-page: https://github.com/Harvard90873/data_structures
Author: Harvard90873
Author-email: harvard90873@gmail.com
License: MIT
Platform: UNKNOWN
Classifier: License :: OSI Approved :: MIT License
Classifier: Programming Language :: Python :: 3.9
Classifier: Programming Language :: Python :: 3
Requires-Dist: importlib-resources
Requires-Dist: python-algorithms-3x
Requires-Dist: termcolor
